emacs_mcp_server.py
mseep_emacs_mcp_server-0.1.4.dist-info/METADATA
mseep_emacs_mcp_server-0.1.4.dist-info/WHEEL
mseep_emacs_mcp_server-0.1.4.dist-info/top_level.txt
mseep_emacs_mcp_server-0.1.4.dist-info/RECORD
