Metadata-Version: 2.4
Name: mseep-emacs-mcp-server
Version: 0.1.4
Summary: Model Context Protocol (MCP) server for Emacs
Author-email: mseep <support@skydeck.ai>
Requires-Python: >=3.12
Requires-Dist: mcp[cli]>=1.6.0
Requires-Dist: smartfunc>=0.2.0
Provides-Extra: dev
Requires-Dist: ruff; extra == "dev"
